payda/__init__.py
payda-0.1.0.dist-info/LICENSE.txt
payda-0.1.0.dist-info/METADATA
payda-0.1.0.dist-info/WHEEL
payda-0.1.0.dist-info/top_level.txt
payda-0.1.0.dist-info/RECORD
