Metadata-Version: 2.1
Name: payda
Version: 0.1.0
Summary: a pip-installable package, dogma alares
Home-page: https://bitbucket.org/dogmaalares/pyda/
Author: Cisem Altan
Author-email: cisem.altan@dogmaalares.com
License: MIT
Keywords: example
Platform: UNKNOWN
